w3shi_h1/__init__.py
w3shi_h1-0.0.3.dist-info/METADATA
w3shi_h1-0.0.3.dist-info/WHEEL
w3shi_h1-0.0.3.dist-info/top_level.txt
w3shi_h1-0.0.3.dist-info/RECORD
