Metadata-Version: 2.4
Name: w3shi_h1
Version: 0.0.3
Summary: Demo package for PyPI publishing test
Home-page: https://github.com/slvignesh05/w3shi_h1
Author: Your Name
Author-email: your@email.com
Classifier: Programming Language :: Python :: 3
Classifier: License :: OSI Approved :: MIT License
Requires-Python: >=3.6
Dynamic: author
Dynamic: author-email
Dynamic: classifier
Dynamic: description
Dynamic: description-content-type
Dynamic: home-page
Dynamic: requires-python
Dynamic: summary
